tm_visionone/__init__.py
tm_visionone/client.py
tm_visionone-0.1.0.dist-info/licenses/LICENSE
tm_visionone-0.1.0.dist-info/METADATA
tm_visionone-0.1.0.dist-info/WHEEL
tm_visionone-0.1.0.dist-info/top_level.txt
tm_visionone-0.1.0.dist-info/RECORD
