Metadata-Version: 2.4
Name: tm-visionone
Version: 0.1.0
Summary: Python SDK for Trend Micro Vision One
Author-email: Sai Kumar Gandhi <saikumargandhi33@gmail.com>
License-Expression: MIT
Project-URL: Homepage, https://github.com/saikumargandhi/tm-visionone
Keywords: trendmicro,visionone,xdr,security,sdk,ioc,trend micro
Classifier: Intended Audience :: Developers
Classifier: Topic :: Security
Classifier: Programming Language :: Python :: 3
Requires-Python: >=3.8
License-File: LICENSE
Requires-Dist: requests>=2.31.0
Dynamic: license-file
